[
  {
    "taskid": 43,
    "shortname": "s3",
    "difficulty": "einfach",
    "points": 10,
    "categories": ["IO"],
    "skills": [
      { "name": "IO", "points": 10 },
      { "name": "STRING", "points": 0 },
      { "name": "DATA", "points": 0 },
      { "name": "CONTROL", "points": 0 },
      { "name": "MATH", "points": 0 },
      { "name": "POINTER", "points": 0 },
      { "name": "ARRAYS", "points": 0 },
      { "name": "MEMORY", "points": 0 },
      { "name": "MODULE", "points": 0 },
      { "name": "STRUCTS", "points": 0 }
    ]
  },
  {
    "taskid": 44,
    "shortname": "s4",
    "difficulty": "einfach",
    "points": 10,
    "categories": ["IO"],
    "skills": [
      { "name": "IO", "points": 10 },
      { "name": "STRING", "points": 0 },
      { "name": "DATA", "points": 0 },
      { "name": "CONTROL", "points": 0 },
      { "name": "MATH", "points": 0 },
      { "name": "POINTER", "points": 0 },
      { "name": "ARRAYS", "points": 0 },
      { "name": "MEMORY", "points": 0 },
      { "name": "MODULE", "points": 0 },
      { "name": "STRUCTS", "points": 0 }
    ]
  },
  {
    "taskid": 45,
    "shortname": "s5",
    "difficulty": "einfach",
    "points": 10,
    "categories": ["IO", "CONTROL"],
    "skills": [
      { "name": "IO", "points": 10 },
      { "name": "STRING", "points": 0 },
      { "name": "DATA", "points": 0 },
      { "name": "CONTROL", "points": 10 },
      { "name": "MATH", "points": 0 },
      { "name": "POINTER", "points": 0 },
      { "name": "ARRAYS", "points": 0 },
      { "name": "MEMORY", "points": 0 },
      { "name": "MODULE", "points": 0 },
      { "name": "STRUCTS", "points": 0 }
    ]
  },
  {
    "taskid": 46,
    "shortname": "s6",
    "difficulty": "mittel",
    "points": 20,
    "categories": ["IO", "CONTROL", "POINTER"],
    "skills": [
      { "name": "IO", "points": 20 },
      { "name": "STRING", "points": 0 },
      { "name": "DATA", "points": 0 },
      { "name": "CONTROL", "points": 20 },
      { "name": "MATH", "points": 0 },
      { "name": "POINTER", "points": 20 },
      { "name": "ARRAYS", "points": 0 },
      { "name": "MEMORY", "points": 0 },
      { "name": "MODULE", "points": 0 },
      { "name": "STRUCTS", "points": 0 }
    ]
  },
  {
    "taskid": 50,
    "shortname": "s9",
    "difficulty": "mittel",
    "points": 20,
    "categories": ["IO", "DATA", "CONTROL", "ARRAYS"],
    "skills": [
      { "name": "IO", "points": 20 },
      { "name": "STRING", "points": 0 },
      { "name": "DATA", "points": 20 },
      { "name": "CONTROL", "points": 20 },
      { "name": "MATH", "points": 0 },
      { "name": "POINTER", "points": 0 },
      { "name": "ARRAYS", "points": 20 },
      { "name": "MEMORY", "points": 0 },
      { "name": "MODULE", "points": 0 },
      { "name": "STRUCTS", "points": 0 }
    ]
  },
  {
    "taskid": 52,
    "shortname": "s11",
    "difficulty": "mittel",
    "points": 20,
    "categories": ["IO", "CONTROL", "MATH"],
    "skills": [
      { "name": "IO", "points": 20 },
      { "name": "STRING", "points": 0 },
      { "name": "DATA", "points": 0 },
      { "name": "CONTROL", "points": 20 },
      { "name": "MATH", "points": 20 },
      { "name": "POINTER", "points": 0 },
      { "name": "ARRAYS", "points": 0 },
      { "name": "MEMORY", "points": 0 },
      { "name": "MODULE", "points": 0 },
      { "name": "STRUCTS", "points": 0 }
    ]
  },
  {
    "taskid": 55,
    "shortname": "e12",
    "difficulty": "einfach",
    "points": 10,
    "categories": ["IO", "MODULE"],
    "skills": [
      { "name": "IO", "points": 10 },
      { "name": "STRING", "points": 0 },
      { "name": "DATA", "points": 0 },
      { "name": "CONTROL", "points": 0 },
      { "name": "MATH", "points": 0 },
      { "name": "POINTER", "points": 0 },
      { "name": "ARRAYS", "points": 0 },
      { "name": "MEMORY", "points": 0 },
      { "name": "MODULE", "points": 10 },
      { "name": "STRUCTS", "points": 0 }
    ]
  },
  {
    "taskid": 59,
    "shortname": "e2",
    "difficulty": "einfach",
    "points": 10,
    "categories": ["IO", "ARRAYS"],
    "skills": [
      { "name": "IO", "points": 10 },
      { "name": "STRING", "points": 0 },
      { "name": "DATA", "points": 0 },
      { "name": "CONTROL", "points": 0 },
      { "name": "MATH", "points": 0 },
      { "name": "POINTER", "points": 0 },
      { "name": "ARRAYS", "points": 10 },
      { "name": "MEMORY", "points": 0 },
      { "name": "MODULE", "points": 0 },
      { "name": "STRUCTS", "points": 0 }
    ]
  },
  {
    "taskid": 60,
    "shortname": "e3",
    "difficulty": "einfach",
    "points": 10,
    "categories": ["IO", "STRING"],
    "skills": [
      { "name": "IO", "points": 10 },
      { "name": "STRING", "points": 10 },
      { "name": "DATA", "points": 0 },
      { "name": "CONTROL", "points": 0 },
      { "name": "MATH", "points": 0 },
      { "name": "POINTER", "points": 0 },
      { "name": "ARRAYS", "points": 0 },
      { "name": "MEMORY", "points": 0 },
      { "name": "MODULE", "points": 0 },
      { "name": "STRUCTS", "points": 0 }
    ]
  },
  {
    "taskid": 61,
    "shortname": "e5",
    "difficulty": "schwierig",
    "points": 40,
    "categories": ["IO", "MATH", "ARRAYS"],
    "skills": [
      { "name": "IO", "points": 40 },
      { "name": "STRING", "points": 0 },
      { "name": "DATA", "points": 0 },
      { "name": "CONTROL", "points": 0 },
      { "name": "MATH", "points": 40 },
      { "name": "POINTER", "points": 0 },
      { "name": "ARRAYS", "points": 40 },
      { "name": "MEMORY", "points": 0 },
      { "name": "MODULE", "points": 0 },
      { "name": "STRUCTS", "points": 0 }
    ]
  },
  {
    "taskid": 49,
    "shortname": "s8",
    "difficulty": "mittel",
    "points": 20,
    "categories": ["STRING", "MATH"],
    "skills": [
      { "name": "IO", "points": 0 },
      { "name": "STRING", "points": 20 },
      { "name": "DATA", "points": 0 },
      { "name": "CONTROL", "points": 0 },
      { "name": "MATH", "points": 20 },
      { "name": "POINTER", "points": 0 },
      { "name": "ARRAYS", "points": 0 },
      { "name": "MEMORY", "points": 0 },
      { "name": "MODULE", "points": 0 },
      { "name": "STRUCTS", "points": 0 }
    ]
  },
  {
    "taskid": 51,
    "shortname": "s10",
    "difficulty": "einfach",
    "points": 10,
    "categories": ["STRING"],
    "skills": [
      { "name": "IO", "points": 0 },
      { "name": "STRING", "points": 10 },
      { "name": "DATA", "points": 0 },
      { "name": "CONTROL", "points": 0 },
      { "name": "MATH", "points": 0 },
      { "name": "POINTER", "points": 0 },
      { "name": "ARRAYS", "points": 0 },
      { "name": "MEMORY", "points": 0 },
      { "name": "MODULE", "points": 0 },
      { "name": "STRUCTS", "points": 0 }
    ]
  },
  {
    "taskid": 62,
    "shortname": "e6",
    "difficulty": "schwierig",
    "points": 40,
    "categories": ["STRING", "CONTROL", "MATH"],
    "skills": [
      { "name": "IO", "points": 0 },
      { "name": "STRING", "points": 40 },
      { "name": "DATA", "points": 0 },
      { "name": "CONTROL", "points": 40 },
      { "name": "MATH", "points": 40 },
      { "name": "POINTER", "points": 0 },
      { "name": "ARRAYS", "points": 0 },
      { "name": "MEMORY", "points": 0 },
      { "name": "MODULE", "points": 0 },
      { "name": "STRUCTS", "points": 0 }
    ]
  },
  {
    "taskid": 63,
    "shortname": "e8",
    "difficulty": "mittel",
    "points": 20,
    "categories": ["STRING", "CONTROL", "ARRAYS"],
    "skills": [
      { "name": "IO", "points": 0 },
      { "name": "STRING", "points": 20 },
      { "name": "DATA", "points": 0 },
      { "name": "CONTROL", "points": 20 },
      { "name": "MATH", "points": 0 },
      { "name": "POINTER", "points": 0 },
      { "name": "ARRAYS", "points": 20 },
      { "name": "MEMORY", "points": 0 },
      { "name": "MODULE", "points": 0 },
      { "name": "STRUCTS", "points": 0 }
    ]
  },
  {
    "taskid": 71,
    "shortname": "z2",
    "difficulty": "mittel",
    "points": 20,
    "categories": ["STRING", "ARRAYS"],
    "skills": [
      { "name": "IO", "points": 0 },
      { "name": "STRING", "points": 20 },
      { "name": "DATA", "points": 0 },
      { "name": "CONTROL", "points": 0 },
      { "name": "MATH", "points": 0 },
      { "name": "POINTER", "points": 0 },
      { "name": "ARRAYS", "points": 20 },
      { "name": "MEMORY", "points": 0 },
      { "name": "MODULE", "points": 0 },
      { "name": "STRUCTS", "points": 0 }
    ]
  },
  {
    "taskid": 74,
    "shortname": "z4",
    "difficulty": "schwierig",
    "points": 40,
    "categories": ["STRING", "POINTER"],
    "skills": [
      { "name": "IO", "points": 0 },
      { "name": "STRING", "points": 40 },
      { "name": "DATA", "points": 0 },
      { "name": "CONTROL", "points": 0 },
      { "name": "MATH", "points": 0 },
      { "name": "POINTER", "points": 40 },
      { "name": "ARRAYS", "points": 0 },
      { "name": "MEMORY", "points": 0 },
      { "name": "MODULE", "points": 0 },
      { "name": "STRUCTS", "points": 0 }
    ]
  },
  {
    "taskid": 75,
    "shortname": "z7",
    "difficulty": "klausur",
    "points": 80,
    "categories": ["STRING", "POINTER", "MEMORY"],
    "skills": [
      { "name": "IO", "points": 0 },
      { "name": "STRING", "points": 80 },
      { "name": "DATA", "points": 0 },
      { "name": "CONTROL", "points": 0 },
      { "name": "MATH", "points": 0 },
      { "name": "POINTER", "points": 80 },
      { "name": "ARRAYS", "points": 0 },
      { "name": "MEMORY", "points": 80 },
      { "name": "MODULE", "points": 0 },
      { "name": "STRUCTS", "points": 0 }
    ]
  },
  {
    "taskid": 82,
    "shortname": "k1",
    "difficulty": "klausur",
    "points": 80,
    "categories": ["STRING"],
    "skills": [
      { "name": "IO", "points": 0 },
      { "name": "STRING", "points": 80 },
      { "name": "DATA", "points": 0 },
      { "name": "CONTROL", "points": 0 },
      { "name": "MATH", "points": 0 },
      { "name": "POINTER", "points": 0 },
      { "name": "ARRAYS", "points": 0 },
      { "name": "MEMORY", "points": 0 },
      { "name": "MODULE", "points": 0 },
      { "name": "STRUCTS", "points": 0 }
    ]
  },
  {
    "taskid": 79,
    "shortname": "z5",
    "difficulty": "klausur",
    "points": 80,
    "categories": ["DATA", "POINTER"],
    "skills": [
      { "name": "IO", "points": 0 },
      { "name": "STRING", "points": 0 },
      { "name": "DATA", "points": 80 },
      { "name": "CONTROL", "points": 0 },
      { "name": "MATH", "points": 0 },
      { "name": "POINTER", "points": 80 },
      { "name": "ARRAYS", "points": 0 },
      { "name": "MEMORY", "points": 0 },
      { "name": "MODULE", "points": 0 },
      { "name": "STRUCTS", "points": 0 }
    ]
  },
  {
    "taskid": 47,
    "shortname": "s7",
    "difficulty": "einfach",
    "points": 10,
    "categories": ["CONTROL", "MATH"],
    "skills": [
      { "name": "IO", "points": 0 },
      { "name": "STRING", "points": 0 },
      { "name": "DATA", "points": 0 },
      { "name": "CONTROL", "points": 10 },
      { "name": "MATH", "points": 10 },
      { "name": "POINTER", "points": 0 },
      { "name": "ARRAYS", "points": 0 },
      { "name": "MEMORY", "points": 0 },
      { "name": "MODULE", "points": 0 },
      { "name": "STRUCTS", "points": 0 }
    ]
  },
  {
    "taskid": 58,
    "shortname": "s23",
    "difficulty": "schwierig",
    "points": 40,
    "categories": ["CONTROL", "MATH", "ARRAYS"],
    "skills": [
      { "name": "IO", "points": 0 },
      { "name": "STRING", "points": 0 },
      { "name": "DATA", "points": 0 },
      { "name": "CONTROL", "points": 40 },
      { "name": "MATH", "points": 40 },
      { "name": "POINTER", "points": 0 },
      { "name": "ARRAYS", "points": 40 },
      { "name": "MEMORY", "points": 0 },
      { "name": "MODULE", "points": 0 },
      { "name": "STRUCTS", "points": 0 }
    ]
  },
  {
    "taskid": 65,
    "shortname": "e13",
    "difficulty": "mittel",
    "points": 20,
    "categories": ["CONTROL", "MATH"],
    "skills": [
      { "name": "IO", "points": 0 },
      { "name": "STRING", "points": 0 },
      { "name": "DATA", "points": 0 },
      { "name": "CONTROL", "points": 20 },
      { "name": "MATH", "points": 20 },
      { "name": "POINTER", "points": 0 },
      { "name": "ARRAYS", "points": 0 },
      { "name": "MEMORY", "points": 0 },
      { "name": "MODULE", "points": 0 },
      { "name": "STRUCTS", "points": 0 }
    ]
  },
  {
    "taskid": 69,
    "shortname": "e26",
    "difficulty": "schwierig",
    "points": 40,
    "categories": ["CONTROL", "ARRAYS"],
    "skills": [
      { "name": "IO", "points": 0 },
      { "name": "STRING", "points": 0 },
      { "name": "DATA", "points": 0 },
      { "name": "CONTROL", "points": 40 },
      { "name": "MATH", "points": 0 },
      { "name": "POINTER", "points": 0 },
      { "name": "ARRAYS", "points": 40 },
      { "name": "MEMORY", "points": 0 },
      { "name": "MODULE", "points": 0 },
      { "name": "STRUCTS", "points": 0 }
    ]
  },
  {
    "taskid": 76,
    "shortname": "e22",
    "difficulty": "mittel",
    "points": 20,
    "categories": ["CONTROL", "ARRAYS"],
    "skills": [
      { "name": "IO", "points": 0 },
      { "name": "STRING", "points": 0 },
      { "name": "DATA", "points": 0 },
      { "name": "CONTROL", "points": 20 },
      { "name": "MATH", "points": 0 },
      { "name": "POINTER", "points": 0 },
      { "name": "ARRAYS", "points": 20 },
      { "name": "MEMORY", "points": 0 },
      { "name": "MODULE", "points": 0 },
      { "name": "STRUCTS", "points": 0 }
    ]
  },
  {
    "taskid": 80,
    "shortname": "z6",
    "difficulty": "einfach",
    "points": 10,
    "categories": ["CONTROL", "MATH"],
    "skills": [
      { "name": "IO", "points": 0 },
      { "name": "STRING", "points": 0 },
      { "name": "DATA", "points": 0 },
      { "name": "CONTROL", "points": 10 },
      { "name": "MATH", "points": 10 },
      { "name": "POINTER", "points": 0 },
      { "name": "ARRAYS", "points": 0 },
      { "name": "MEMORY", "points": 0 },
      { "name": "MODULE", "points": 0 },
      { "name": "STRUCTS", "points": 0 }
    ]
  },
  {
    "taskid": 83,
    "shortname": "k2",
    "difficulty": "schwierig",
    "points": 40,
    "categories": ["CONTROL"],
    "skills": [
      { "name": "IO", "points": 0 },
      { "name": "STRING", "points": 0 },
      { "name": "DATA", "points": 0 },
      { "name": "CONTROL", "points": 40 },
      { "name": "MATH", "points": 0 },
      { "name": "POINTER", "points": 0 },
      { "name": "ARRAYS", "points": 0 },
      { "name": "MEMORY", "points": 0 },
      { "name": "MODULE", "points": 0 },
      { "name": "STRUCTS", "points": 0 }
    ]
  },
  {
    "taskid": 48,
    "shortname": "x1",
    "difficulty": "mittel",
    "points": 20,
    "categories": ["MATH"],
    "skills": [
      { "name": "IO", "points": 0 },
      { "name": "STRING", "points": 0 },
      { "name": "DATA", "points": 0 },
      { "name": "CONTROL", "points": 0 },
      { "name": "MATH", "points": 20 },
      { "name": "POINTER", "points": 0 },
      { "name": "ARRAYS", "points": 0 },
      { "name": "MEMORY", "points": 0 },
      { "name": "MODULE", "points": 0 },
      { "name": "STRUCTS", "points": 0 }
    ]
  },
  {
    "taskid": 53,
    "shortname": "s14",
    "difficulty": "mittel",
    "points": 20,
    "categories": ["MATH", "ARRAYS"],
    "skills": [
      { "name": "IO", "points": 0 },
      { "name": "STRING", "points": 0 },
      { "name": "DATA", "points": 0 },
      { "name": "CONTROL", "points": 0 },
      { "name": "MATH", "points": 20 },
      { "name": "POINTER", "points": 0 },
      { "name": "ARRAYS", "points": 20 },
      { "name": "MEMORY", "points": 0 },
      { "name": "MODULE", "points": 0 },
      { "name": "STRUCTS", "points": 0 }
    ]
  },
  {
    "taskid": 57,
    "shortname": "s13",
    "difficulty": "schwierig",
    "points": 40,
    "categories": ["MATH", "ARRAYS"],
    "skills": [
      { "name": "IO", "points": 0 },
      { "name": "STRING", "points": 0 },
      { "name": "DATA", "points": 0 },
      { "name": "CONTROL", "points": 0 },
      { "name": "MATH", "points": 40 },
      { "name": "POINTER", "points": 0 },
      { "name": "ARRAYS", "points": 40 },
      { "name": "MEMORY", "points": 0 },
      { "name": "MODULE", "points": 0 },
      { "name": "STRUCTS", "points": 0 }
    ]
  },
  {
    "taskid": 70,
    "shortname": "e27",
    "difficulty": "schwierig",
    "points": 40,
    "categories": ["MATH", "POINTER", "MEMORY"],
    "skills": [
      { "name": "IO", "points": 0 },
      { "name": "STRING", "points": 0 },
      { "name": "DATA", "points": 0 },
      { "name": "CONTROL", "points": 0 },
      { "name": "MATH", "points": 40 },
      { "name": "POINTER", "points": 40 },
      { "name": "ARRAYS", "points": 0 },
      { "name": "MEMORY", "points": 40 },
      { "name": "MODULE", "points": 0 },
      { "name": "STRUCTS", "points": 0 }
    ]
  },
  {
    "taskid": 81,
    "shortname": "s17",
    "difficulty": "einfach",
    "points": 10,
    "categories": ["MATH"],
    "skills": [
      { "name": "IO", "points": 0 },
      { "name": "STRING", "points": 0 },
      { "name": "DATA", "points": 0 },
      { "name": "CONTROL", "points": 0 },
      { "name": "MATH", "points": 10 },
      { "name": "POINTER", "points": 0 },
      { "name": "ARRAYS", "points": 0 },
      { "name": "MEMORY", "points": 0 },
      { "name": "MODULE", "points": 0 },
      { "name": "STRUCTS", "points": 0 }
    ]
  },
  {
    "taskid": 72,
    "shortname": "s20",
    "difficulty": "schwierig",
    "points": 40,
    "categories": ["MATH", "ARRAYS"],
    "skills": [
      { "name": "IO", "points": 0 },
      { "name": "STRING", "points": 0 },
      { "name": "DATA", "points": 0 },
      { "name": "CONTROL", "points": 0 },
      { "name": "MATH", "points": 40 },
      { "name": "POINTER", "points": 0 },
      { "name": "ARRAYS", "points": 40 },
      { "name": "MEMORY", "points": 0 },
      { "name": "MODULE", "points": 0 },
      { "name": "STRUCTS", "points": 0 }
    ]
  },
  {
    "taskid": 73,
    "shortname": "e21",
    "difficulty": "mittel",
    "points": 20,
    "categories": ["POINTER", "ARRAYS"],
    "skills": [
      { "name": "IO", "points": 0 },
      { "name": "STRING", "points": 0 },
      { "name": "DATA", "points": 0 },
      { "name": "CONTROL", "points": 0 },
      { "name": "MATH", "points": 0 },
      { "name": "POINTER", "points": 20 },
      { "name": "ARRAYS", "points": 20 },
      { "name": "MEMORY", "points": 0 },
      { "name": "MODULE", "points": 0 },
      { "name": "STRUCTS", "points": 0 }
    ]
  },
  {
    "taskid": 77,
    "shortname": "e23",
    "difficulty": "schwierig",
    "points": 40,
    "categories": ["ARRAYS"],
    "skills": [
      { "name": "IO", "points": 0 },
      { "name": "STRING", "points": 0 },
      { "name": "DATA", "points": 0 },
      { "name": "CONTROL", "points": 0 },
      { "name": "MATH", "points": 0 },
      { "name": "POINTER", "points": 0 },
      { "name": "ARRAYS", "points": 40 },
      { "name": "MEMORY", "points": 0 },
      { "name": "MODULE", "points": 0 },
      { "name": "STRUCTS", "points": 0 }
    ]
  },
  {
    "taskid": 78,
    "shortname": "z8",
    "difficulty": "schwierig",
    "points": 40,
    "categories": ["STRUCTS"],
    "skills": [
      { "name": "IO", "points": 0 },
      { "name": "STRING", "points": 0 },
      { "name": "DATA", "points": 0 },
      { "name": "CONTROL", "points": 0 },
      { "name": "MATH", "points": 0 },
      { "name": "POINTER", "points": 0 },
      { "name": "ARRAYS", "points": 0 },
      { "name": "MEMORY", "points": 0 },
      { "name": "MODULE", "points": 0 },
      { "name": "STRUCTS", "points": 40 }
    ]
  }
]